navytraceback/__init__.py
navytraceback-0.2.0.dist-info/METADATA
navytraceback-0.2.0.dist-info/WHEEL
navytraceback-0.2.0.dist-info/top_level.txt
navytraceback-0.2.0.dist-info/RECORD
