Metadata-Version: 2.4
Name: navytraceback
Version: 0.2.0
Summary: A XP-style traceback handler
License: MIT
Classifier: Programming Language :: Python :: 3
Classifier: Operating System :: OS Independent
Classifier: Topic :: Software Development :: Debuggers
Requires-Python: >=3.7
